fs/wrapcifs/__init__.py
fs/wrapcifs/py.typed
fs/wrapcifs/wrapcifs.py
fs_wrapcifs-0.1.0.dist-info/LICENSE
fs_wrapcifs-0.1.0.dist-info/METADATA
fs_wrapcifs-0.1.0.dist-info/WHEEL
fs_wrapcifs-0.1.0.dist-info/RECORD
